olmocr/__init__.py
olmocr/check.py
olmocr/datatypes.py
olmocr/image_utils.py
olmocr/metrics.py
olmocr/pipeline.py
olmocr/py.typed
olmocr/repeatdetect.py
olmocr/s3_utils.py
olmocr/version.py
olmocr/work_queue.py
olmocr/bench/__init__.py
olmocr/bench/benchmark.py
olmocr/bench/convert.py
olmocr/bench/prompts.py
olmocr/bench/report.py
olmocr/bench/review_app.py
olmocr/bench/review_app_latex.py
olmocr/bench/tests.py
olmocr/bench/utils.py
olmocr/bench/katex/__init__.py
olmocr/bench/katex/auto-render.min.js
olmocr/bench/katex/katex.min.css
olmocr/bench/katex/katex.min.js
olmocr/bench/katex/render.py
olmocr/bench/miners/check_headers_footers.py
olmocr/bench/miners/check_multicolumn.py
olmocr/bench/miners/check_old_scans_math.py
olmocr/bench/miners/cleanup_data.py
olmocr/bench/miners/cleanup_urls.py
olmocr/bench/miners/delete_rejected.py
olmocr/bench/miners/download_math.py
olmocr/bench/miners/mine_blank_pages_gpt.py
olmocr/bench/miners/mine_diffs.py
olmocr/bench/miners/mine_headers_footers.py
olmocr/bench/miners/mine_long_tiny_text.py
olmocr/bench/miners/mine_math.py
olmocr/bench/miners/mine_multi_column.py
olmocr/bench/miners/mine_multilingual_gpt.py
olmocr/bench/miners/mine_old_scan_pdf.py
olmocr/bench/miners/mine_old_scans.py
olmocr/bench/miners/mine_old_scans_math.py
olmocr/bench/miners/mine_reading_order.py
olmocr/bench/miners/mine_tables_gemini.py
olmocr/bench/miners/mine_tables_gpt.py
olmocr/bench/miners/mine_tables_gpt_simple.py
olmocr/bench/miners/pick_mediod.py
olmocr/bench/runners/__init__.py
olmocr/bench/runners/run_chatgpt.py
olmocr/bench/runners/run_claude.py
olmocr/bench/runners/run_docling.py
olmocr/bench/runners/run_gemini.py
olmocr/bench/runners/run_gotocr.py
olmocr/bench/runners/run_marker.py
olmocr/bench/runners/run_mineru.py
olmocr/bench/runners/run_mistral.py
olmocr/bench/runners/run_nanonetsocr.py
olmocr/bench/runners/run_nanonetsocr_2.py
olmocr/bench/runners/run_olmocr_pipeline.py
olmocr/bench/runners/run_paddlepaddle.py
olmocr-0.4.25.dist-info/licenses/LICENSE
olmocr-0.4.25.dist-info/METADATA
olmocr-0.4.25.dist-info/WHEEL
olmocr-0.4.25.dist-info/top_level.txt
olmocr-0.4.25.dist-info/RECORD
