Metadata-Version: 2.4
Name: olmocr
Version: 0.4.25
Summary: Fast, efficient, and high quality OCR powered by open visual language models
Author-email: Allen Institute for Artificial Intelligence <jakep@allenai.org>
License:                                  Apache License
Project-URL: Homepage, https://github.com/allenai/olmocr
Project-URL: Repository, https://github.com/allenai/olmocr
Project-URL: Changelog, https://github.com/allenai/olmocr/blob/main/CHANGELOG.md
Classifier: Intended Audience :: Science/Research
Classifier: Development Status :: 3 - Alpha
Classifier: License :: OSI Approved :: Apache Software License
Classifier: Programming Language :: Python :: 3
Classifier: Topic :: Scientific/Engineering :: Artificial Intelligence
Requires-Python: >=3.11
License-File: LICENSE
Requires-Dist: cached-path
Requires-Dist: smart_open
Requires-Dist: pypdf>=5.2.0
Requires-Dist: pypdfium2
Requires-Dist: cryptography
Requires-Dist: lingua-language-detector
Requires-Dist: Pillow
Requires-Dist: ftfy
Requires-Dist: bleach
Requires-Dist: markdown2
Requires-Dist: markdownify
Requires-Dist: filelock
Requires-Dist: orjson
Requires-Dist: requests
Requires-Dist: zstandard
Requires-Dist: boto3
Requires-Dist: httpx
Requires-Dist: torch>=2.7.0
Requires-Dist: transformers==4.57.3
Requires-Dist: beaker-py
Provides-Extra: gpu
Requires-Dist: vllm==0.11.2; extra == "gpu"
Provides-Extra: dev
Requires-Dist: ruff; extra == "dev"
Requires-Dist: mypy; extra == "dev"
Requires-Dist: black; extra == "dev"
Requires-Dist: isort; extra == "dev"
Requires-Dist: pytest; extra == "dev"
Requires-Dist: pytest-sphinx; extra == "dev"
Requires-Dist: pytest-cov; extra == "dev"
Requires-Dist: pytest-asyncio; extra == "dev"
Requires-Dist: twine>=1.11.0; extra == "dev"
Requires-Dist: build; extra == "dev"
Requires-Dist: setuptools; extra == "dev"
Requires-Dist: wheel; extra == "dev"
Requires-Dist: Sphinx<7.1.0,>=4.3.0; extra == "dev"
Requires-Dist: furo==2023.7.26; extra == "dev"
Requires-Dist: myst-parser<2.1,>=1.0; extra == "dev"
Requires-Dist: sphinx-copybutton==0.5.2; extra == "dev"
Requires-Dist: sphinx-autobuild==2021.3.14; extra == "dev"
Requires-Dist: sphinx-autodoc-typehints==1.23.3; extra == "dev"
Requires-Dist: packaging; extra == "dev"
Requires-Dist: necessary; extra == "dev"
Requires-Dist: peft; extra == "dev"
Requires-Dist: datasets; extra == "dev"
Requires-Dist: omegaconf; extra == "dev"
Requires-Dist: spacy; extra == "dev"
Requires-Dist: wandb; extra == "dev"
Requires-Dist: trl; extra == "dev"
Provides-Extra: bench
Requires-Dist: tinyhost; extra == "bench"
Requires-Dist: fuzzysearch; extra == "bench"
Requires-Dist: rapidfuzz; extra == "bench"
Requires-Dist: sequence_align; extra == "bench"
Requires-Dist: syntok; extra == "bench"
Requires-Dist: openai; extra == "bench"
Requires-Dist: google-genai; extra == "bench"
Requires-Dist: anthropic; extra == "bench"
Requires-Dist: playwright; extra == "bench"
Requires-Dist: mistralai; extra == "bench"
Requires-Dist: lxml; extra == "bench"
Requires-Dist: flask; extra == "bench"
Provides-Extra: train
Requires-Dist: torch; extra == "train"
Requires-Dist: torchvision; extra == "train"
Requires-Dist: accelerate; extra == "train"
Requires-Dist: trl; extra == "train"
Requires-Dist: peft; extra == "train"
Requires-Dist: wandb; extra == "train"
Requires-Dist: omegaconf; extra == "train"
Requires-Dist: einops; extra == "train"
Requires-Dist: augraphy; extra == "train"
Provides-Extra: elo
Requires-Dist: numpy; extra == "elo"
Requires-Dist: scipy; extra == "elo"
Requires-Dist: pandas; extra == "elo"
Requires-Dist: matplotlib; extra == "elo"
Dynamic: license-file
